sceneweaver/__init__.py
sceneweaver/__main__.py
sceneweaver/_version.py
sceneweaver/app.py
sceneweaver/cache.py
sceneweaver/errors.py
sceneweaver/font.py
sceneweaver/generator.py
sceneweaver/loader.py
sceneweaver/recorder.py
sceneweaver/renderer.py
sceneweaver/template.py
sceneweaver/template_manager.py
sceneweaver/resources/templates/simple_title/README.md
sceneweaver/resources/templates/simple_title/example.yaml
sceneweaver/resources/templates/simple_title/params.yaml
sceneweaver/resources/templates/simple_title/screenshot.png
sceneweaver/resources/templates/simple_title/template.yaml
sceneweaver/resources/templates/simple_title/title_only.svg
sceneweaver/resources/templates/slide_sequence/README.md
sceneweaver/resources/templates/slide_sequence/example.yaml
sceneweaver/resources/templates/slide_sequence/params.yaml
sceneweaver/resources/templates/slide_sequence/screenshot.png
sceneweaver/resources/templates/slide_sequence/slide.svg
sceneweaver/resources/templates/slide_sequence/template.yaml
sceneweaver/resources/templates/title_and_subtitle/README.md
sceneweaver/resources/templates/title_and_subtitle/animated_title.svg
sceneweaver/resources/templates/title_and_subtitle/example.yaml
sceneweaver/resources/templates/title_and_subtitle/params.yaml
sceneweaver/resources/templates/title_and_subtitle/screenshot.png
sceneweaver/resources/templates/title_and_subtitle/template.yaml
sceneweaver/spec/__init__.py
sceneweaver/spec/audio_spec.py
sceneweaver/spec/video_settings.py
sceneweaver/spec/video_spec.py
sceneweaver/spec/zoom_spec.py
sceneweaver/spec/annotation/__init__.py
sceneweaver/spec/annotation/arrow_annotation.py
sceneweaver/spec/annotation/base_annotation.py
sceneweaver/spec/annotation/highlight_annotation.py
sceneweaver/spec/annotation/text_annotation.py
sceneweaver/spec/effect/__init__.py
sceneweaver/spec/effect/base_effect.py
sceneweaver/spec/effect/fade_effect.py
sceneweaver/spec/scene/__init__.py
sceneweaver/spec/scene/base_scene.py
sceneweaver-0.5.dist-info/METADATA
sceneweaver-0.5.dist-info/WHEEL
sceneweaver-0.5.dist-info/entry_points.txt
sceneweaver-0.5.dist-info/top_level.txt
sceneweaver-0.5.dist-info/RECORD
