Metadata-Version: 2.4
Name: sceneweaver
Version: 0.5
Summary: A tool for creating videos from YAML specification files
Author: SceneWeaver Team
License-Expression: MIT
Project-URL: Homepage, https://github.com/yourusername/sceneweaver
Project-URL: Repository, https://github.com/yourusername/sceneweaver
Project-URL: Issues, https://github.com/yourusername/sceneweaver/issues
Keywords: video,moviepy,yaml,editing
Classifier: Development Status :: 3 - Alpha
Classifier: Intended Audience :: Developers
Classifier: Programming Language :: Python :: 3
Classifier: Programming Language :: Python :: 3.8
Classifier: Programming Language :: Python :: 3.9
Classifier: Programming Language :: Python :: 3.10
Classifier: Programming Language :: Python :: 3.11
Classifier: Programming Language :: Python :: 3.12
Classifier: Topic :: Multimedia :: Video
Classifier: Topic :: Software Development :: Libraries :: Python Modules
Requires-Python: >=3.8
Requires-Dist: moviepy>=2.0.0
Requires-Dist: ruamel.yaml<0.19,>=0.17
Requires-Dist: platformdirs<5,>=4.5.0
Requires-Dist: sounddevice
Requires-Dist: noisereduce
Requires-Dist: cairosvg
Requires-Dist: jinja2
Requires-Dist: Pillow>=10.0
Requires-Dist: numpy>=1.20
Requires-Dist: scipy>=1.6
Provides-Extra: dev
Requires-Dist: pytest>=7.0; extra == "dev"
Requires-Dist: pytest-cov>=4.0; extra == "dev"
Requires-Dist: black>=22.0; extra == "dev"
Requires-Dist: flake8; extra == "dev"
Requires-Dist: pyflakes; extra == "dev"
Requires-Dist: pyright; extra == "dev"
Requires-Dist: ruff; extra == "dev"
Requires-Dist: pre-commit; extra == "dev"
